{
"type": "FeatureCollection",
"name": "Vihara",
"crs": { "type": "name", "properties": { "name": "urn:ogc:def:crs:OGC:1.3:CRS84" } },
"features": [
{ "type": "Feature", "properties": { "objectid": 430, "fgsprp": 4, "metadata": null, "fcode": "GF01030020", "namaobj": "WIHARA MAHAWELAS ASIH", "srs_id": 0, "remark": "WIHARA", "wadmpr": "JAWA TENGAH", "alamat": "JALAN DELTA MAS TENGAH", "laman": "https:\/\/gis.dukcapil.kemendagri.go.id\/" }, "geometry": { "type": "Point", "coordinates": [ 110.412540000072312, -6.959939999920308 ] } },
{ "type": "Feature", "properties": { "objectid": 519, "fgsprp": 4, "metadata": null, "fcode": "GF01030020", "namaobj": "VIHARA GUNUNG PATI", "srs_id": 0, "remark": "WIHARA", "wadmpr": "JAWA TENGAH", "alamat": "JALAN KOL. R. WARSITO SOEGIARTO", "laman": "https:\/\/gis.dukcapil.kemendagri.go.id\/" }, "geometry": { "type": "Point", "coordinates": [ 110.368869999739417, -7.036309999871012 ] } },
{ "type": "Feature", "properties": { "objectid": 870, "fgsprp": 4, "metadata": null, "fcode": "GF01030020", "namaobj": "WIHARA MAVIRA", "srs_id": 0, "remark": "WIHARA", "wadmpr": "JAWA TENGAH", "alamat": "JALAN MARINA", "laman": "https:\/\/gis.dukcapil.kemendagri.go.id\/" }, "geometry": { "type": "Point", "coordinates": [ 110.392540000214822, -6.958440000385139 ] } },
{ "type": "Feature", "properties": { "objectid": 871, "fgsprp": 4, "metadata": null, "fcode": "GF01030020", "namaobj": "WIHARA LOW LI BIO", "srs_id": 0, "remark": "WIHARA", "wadmpr": "JAWA TENGAH", "alamat": "JALAN RORO JONGGRANG TIMUR XIII", "laman": "https:\/\/gis.dukcapil.kemendagri.go.id\/" }, "geometry": { "type": "Point", "coordinates": [ 110.383839999944442, -7.007109999701512 ] } },
{ "type": "Feature", "properties": { "objectid": 924, "fgsprp": 4, "metadata": null, "fcode": "GF01030020", "namaobj": "VIHARA TANAH PUTIH", "srs_id": 0, "remark": "WIHARA", "wadmpr": "JAWA TENGAH", "alamat": "JALAN DR. WAHIDIN", "laman": "https:\/\/gis.dukcapil.kemendagri.go.id\/" }, "geometry": { "type": "Point", "coordinates": [ 110.431680000487475, -7.0104599993584 ] } },
{ "type": "Feature", "properties": { "objectid": 1475, "fgsprp": 4, "metadata": null, "fcode": "GF01030020", "namaobj": "VIHARA MAHAVIRA GRAHA SEMARANG", "srs_id": 0, "remark": "WIHARA", "wadmpr": "JAWA TENGAH", "alamat": "JALAN MARINA", "laman": "https:\/\/gis.dukcapil.kemendagri.go.id\/" }, "geometry": { "type": "Point", "coordinates": [ 110.392469999894629, -6.957840000120734 ] } },
{ "type": "Feature", "properties": { "objectid": 2390, "fgsprp": 4, "metadata": null, "fcode": "GF01030020", "namaobj": "VIHARA MAITREYA", "srs_id": 0, "remark": "WIHARA", "wadmpr": "JAWA TENGAH", "alamat": "JALAN KALIMAS RAYA", "laman": "https:\/\/gis.dukcapil.kemendagri.go.id\/" }, "geometry": { "type": "Point", "coordinates": [ 110.406229999954689, -6.963410000415363 ] } },
{ "type": "Feature", "properties": { "objectid": 4065, "fgsprp": 4, "metadata": null, "fcode": "GF01030020", "namaobj": "VIHARA THAY SIONG KIONG", "srs_id": 0, "remark": "WIHARA", "wadmpr": "JAWA TENGAH", "alamat": "JALAN TAMAN HASANUDIN", "laman": "https:\/\/gis.dukcapil.kemendagri.go.id\/" }, "geometry": { "type": "Point", "coordinates": [ 110.410739999923422, -6.959269999798872 ] } },
{ "type": "Feature", "properties": { "objectid": 4402, "fgsprp": 4, "metadata": null, "fcode": "GF01030020", "namaobj": "VIHARA MAHA WELAS ASIH", "srs_id": 0, "remark": "WIHARA", "wadmpr": "JAWA TENGAH", "alamat": "JALAN TAMAN HASANUDIN", "laman": "https:\/\/gis.dukcapil.kemendagri.go.id\/" }, "geometry": { "type": "Point", "coordinates": [ 110.412229999552594, -6.960329999816802 ] } },
{ "type": "Feature", "properties": { "objectid": 4461, "fgsprp": 4, "metadata": null, "fcode": "GF01030020", "namaobj": "WIHARA BUDI LUHUR SAKTI", "srs_id": 0, "remark": "WIHARA", "wadmpr": "JAWA TENGAH", "alamat": "JALAN TANJUNG MAS RAYA", "laman": "https:\/\/gis.dukcapil.kemendagri.go.id\/" }, "geometry": { "type": "Point", "coordinates": [ 110.404320000200954, -6.954230000670934 ] } },
{ "type": "Feature", "properties": { "objectid": 4581, "fgsprp": 4, "metadata": null, "fcode": "GF01030020", "namaobj": "VIHARA MAHABODHI MAITREYA", "srs_id": 0, "remark": "WIHARA", "wadmpr": "JAWA TENGAH", "alamat": "JALAN LIGU UTARA", "laman": "https:\/\/gis.dukcapil.kemendagri.go.id\/" }, "geometry": { "type": "Point", "coordinates": [ 110.432329999867505, -6.982460000033442 ] } }
]
}
